cluplus/__init__.py
cluplus/configloader.py
cluplus/exceptions.py
cluplus/parsers/click.py
cluplus/parsers/jsonpickle.py
cluplus/parsers/jsonstring.py
cluplus/proxy.py
sdss_cluplus-0.5.2.dist-info/LICENSE.md
sdss_cluplus-0.5.2.dist-info/METADATA
sdss_cluplus-0.5.2.dist-info/WHEEL
sdss_cluplus-0.5.2.dist-info/entry_points.txt
sdss_cluplus-0.5.2.dist-info/RECORD
