Metadata-Version: 2.1
Name: sdss-cluplus
Version: 0.5.2
Summary: Additional functionality for sdss-clu
Home-page: https://github.com/sdss/cluplus
License: BSD-3-Clause
Keywords: astronomy,software
Author: Florian Briegel
Author-email: briegel@mpia.de
Requires-Python: >=3.8,<4.0
Classifier: Intended Audience :: Science/Research
Classifier: License :: OSI Approved :: BSD License
Classifier: Natural Language :: English
Classifier: Operating System :: OS Independent
Classifier: Programming Language :: Python :: 3
Classifier: Programming Language :: Python :: 3.8
Classifier: Programming Language :: Python :: 3.9
Classifier: Programming Language :: Python :: 3.10
Classifier: Programming Language :: Python :: 3.11
Classifier: Programming Language :: Python :: 3.10
Classifier: Programming Language :: Python :: 3.8
Classifier: Programming Language :: Python :: 3.9
Classifier: Topic :: Documentation :: Sphinx
Classifier: Topic :: Software Development :: Libraries :: Python Modules
Requires-Dist: attrdict (>2.0)
Requires-Dist: click-default-group (>=1.2.2,<2.0.0)
Requires-Dist: daemonocle (>=1.1.1,<2.0.0)
Requires-Dist: expandvars (>=0.9.0)
Requires-Dist: jsonpickle (==1.3)
Requires-Dist: sdss-access (>=0.2.3)
Requires-Dist: sdss-clu (>=2.0.0)
Requires-Dist: sdss-tree (>=2.15.2)
Requires-Dist: sdsstools (>=0.4.0)
Project-URL: Documentation, https://sdss-cluplus.readthedocs.org
Project-URL: Repository, https://github.com/sdss/cluplus
